modulereport/__init__.py
modulereport/__main__.py
modulereport/cli.py
modulereport/modulesimported.py
modulereport/test/__init__.py
modulereport/test/test_cli.py
modulereport/test/test_modulesimported.py
modulereport/utils/__init__.py
modulereport/utils/environment.py
modulereport/utils/test/__init__.py
modulereport/utils/test/test_environment.py
modulereport-0.3.9.dist-info/DESCRIPTION.rst
modulereport-0.3.9.dist-info/LICENSE.txt
modulereport-0.3.9.dist-info/METADATA
modulereport-0.3.9.dist-info/RECORD
modulereport-0.3.9.dist-info/WHEEL
modulereport-0.3.9.dist-info/entry_points.txt
modulereport-0.3.9.dist-info/metadata.json
modulereport-0.3.9.dist-info/top_level.txt
