Metadata-Version: 2.0
Name: modulereport
Version: 0.3.9
Summary: 
